tiny_elephant/__init__.py
tiny_elephant/in_memory_cluster.py
tiny_elephant/in_memory_cluster_test.py
tiny_elephant/renappy.py
tiny_elephant-0.1.3.dist-info/LICENSE
tiny_elephant-0.1.3.dist-info/METADATA
tiny_elephant-0.1.3.dist-info/WHEEL
tiny_elephant-0.1.3.dist-info/top_level.txt
tiny_elephant-0.1.3.dist-info/RECORD
