Metadata-Version: 2.1
Name: tiny-elephant
Version: 0.1.3
Summary: In memory based collaborative filtering
Home-page: https://github.com/kyunooh/tiny_elephant
Author: Hyeon-Mook Jerry Choi
Author-email: chm073@gmail.com
License: UNKNOWN
Download-URL: https://github.com/kyunooh/tiny_elephant/archive/v0.1.3.tar.gz
Keywords: clustering,collaborative filtering,redis,in memory based
Platform: UNKNOWN
Classifier: Programming Language :: Python :: 3.4
Classifier: Programming Language :: Python :: 3.5
Classifier: Programming Language :: Python :: 3.6
Classifier: Programming Language :: Python :: 3.7
Requires-Dist: python-snappy
Requires-Dist: redis
Requires-Dist: datasketch
Requires-Dist: simplejson
